django_stisla/__init__.py
django_stisla/admin.py
django_stisla/apps.py
django_stisla/static/admin/.DS_Store
django_stisla/static/admin/assets/css/components.css
django_stisla/static/admin/assets/css/components.css.map
django_stisla/static/admin/assets/css/custom.css
django_stisla/static/admin/assets/css/custom.css.map
django_stisla/static/admin/assets/css/extra.css
django_stisla/static/admin/assets/css/reverse.css
django_stisla/static/admin/assets/css/rtl.css
django_stisla/static/admin/assets/css/style.css
django_stisla/static/admin/assets/css/style.css.map
django_stisla/static/admin/assets/css/skins/reverse.css
django_stisla/static/admin/assets/css/skins/reverse.css.map
django_stisla/static/admin/assets/fonts/nunito-v9-latin-600.eot
django_stisla/static/admin/assets/fonts/nunito-v9-latin-600.svg
django_stisla/static/admin/assets/fonts/nunito-v9-latin-600.ttf
django_stisla/static/admin/assets/fonts/nunito-v9-latin-600.woff
django_stisla/static/admin/assets/fonts/nunito-v9-latin-600.woff2
django_stisla/static/admin/assets/fonts/nunito-v9-latin-700.eot
django_stisla/static/admin/assets/fonts/nunito-v9-latin-700.svg
django_stisla/static/admin/assets/fonts/nunito-v9-latin-700.ttf
django_stisla/static/admin/assets/fonts/nunito-v9-latin-700.woff
django_stisla/static/admin/assets/fonts/nunito-v9-latin-700.woff2
django_stisla/static/admin/assets/fonts/nunito-v9-latin-800.eot
django_stisla/static/admin/assets/fonts/nunito-v9-latin-800.svg
django_stisla/static/admin/assets/fonts/nunito-v9-latin-800.ttf
django_stisla/static/admin/assets/fonts/nunito-v9-latin-800.woff
django_stisla/static/admin/assets/fonts/nunito-v9-latin-800.woff2
django_stisla/static/admin/assets/fonts/nunito-v9-latin-regular.eot
django_stisla/static/admin/assets/fonts/nunito-v9-latin-regular.svg
django_stisla/static/admin/assets/fonts/nunito-v9-latin-regular.ttf
django_stisla/static/admin/assets/fonts/nunito-v9-latin-regular.woff
django_stisla/static/admin/assets/fonts/nunito-v9-latin-regular.woff2
django_stisla-0.0.7.dist-info/LICENSE
django_stisla-0.0.7.dist-info/METADATA
django_stisla-0.0.7.dist-info/WHEEL
django_stisla-0.0.7.dist-info/top_level.txt
django_stisla-0.0.7.dist-info/RECORD
